heroku_guardian/__init__.py
heroku_guardian/bin/__init__.py
heroku_guardian/bin/cli.py
heroku_guardian/bin/version.py
heroku_guardian/checks/__init__.py
heroku_guardian/checks/app_checks.py
heroku_guardian/checks/space_checks.py
heroku_guardian/checks/user_checks.py
heroku_guardian/command/__init__.py
heroku_guardian/command/app.py
heroku_guardian/command/space.py
heroku_guardian/command/user.py
heroku_guardian/resources/__init__.py
heroku_guardian/resources/apps.py
heroku_guardian/resources/spaces.py
heroku_guardian/resources/users.py
heroku_guardian/utils/__init__.py
heroku_guardian/utils/utils.py
heroku_guardian-0.1.0.dist-info/LICENSE
heroku_guardian-0.1.0.dist-info/METADATA
heroku_guardian-0.1.0.dist-info/WHEEL
heroku_guardian-0.1.0.dist-info/entry_points.txt
heroku_guardian-0.1.0.dist-info/top_level.txt
heroku_guardian-0.1.0.dist-info/zip-safe
heroku_guardian-0.1.0.dist-info/RECORD
