Metadata-Version: 2.1
Name: heroku-guardian
Version: 0.1.0
Summary: Simple and easy to use security checks for the Heroku platform.
Home-page: https://github.com/heroku/heroku_guardian
Author: Ashish Patel
Author-email: patel.ashish@salesforce.com
License: UNKNOWN
Keywords: heroku roles policy policies privileges security
Platform: UNKNOWN
Classifier: Programming Language :: Python :: 3
Classifier: License :: OSI Approved :: MIT License
Classifier: Operating System :: OS Independent
Requires-Python: >=3.6
Requires-Dist: click
Requires-Dist: colorama
Requires-Dist: requests
